[
  {"key": "chikorita", "rarity": "common", "value": 100},
  {"key": "bayleef", "rarity": "common", "value": 500},
  {"key": "meganium", "rarity": "uncommon", "value": 1500},
  {"key": "cyndaquil", "rarity": "common", "value": 100},
  {"key": "quilava", "rarity": "common", "value": 500},
  {"key": "typhlosion", "rarity": "rare", "value": 5000},
  {"key": "totodile", "rarity": "common", "value": 100},
  {"key": "croconaw", "rarity": "common", "value": 500},
  {"key": "feraligatr", "rarity": "rare", "value": 5000},
  {"key": "sentret", "rarity": "common", "value": 100},
  {"key": "furret", "rarity": "uncommon", "value": 1500},
  {"key": "hoothoot", "rarity": "common", "value": 100},
  {"key": "noctowl", "rarity": "uncommon", "value": 1500},
  {"key": "ledyba", "rarity": "common", "value": 100},
  {"key": "ledian", "rarity": "uncommon", "value": 1500},
  {"key": "spinarak", "rarity": "common", "value": 100},
  {"key": "ariados", "rarity": "uncommon", "value": 1500},
  {"key": "crobat", "rarity": "rare", "value": 5000},
  {"key": "chinchou", "rarity": "common", "value": 100},
  {"key": "lanturn", "rarity": "uncommon", "value": 1500},
  {"key": "pichu", "rarity": "rare", "value": 5000},
  {"key": "cleffa", "rarity": "common", "value": 100},
  {"key": "igglybuff", "rarity": "common", "value": 100},
  {"key": "togepi", "rarity": "rare", "value": 5000},
  {"key": "togetic", "rarity": "epic", "value": 15000},
  {"key": "natu", "rarity": "common", "value": 100},
  {"key": "xatu", "rarity": "uncommon", "value": 1500},
  {"key": "mareep", "rarity": "common", "value": 100},
  {"key": "flaaffy", "rarity": "common", "value": 500},
  {"key": "ampharos", "rarity": "rare", "value": 5000},
  {"key": "bellossom", "rarity": "uncommon", "value": 1500},
  {"key": "marill", "rarity": "common", "value": 100},
  {"key": "azumarill", "rarity": "rare", "value": 5000},
  {"key": "sudowoodo", "rarity": "rare", "value": 5000},
  {"key": "politoed", "rarity": "epic", "value": 15000},
  {"key": "hoppip", "rarity": "common", "value": 100},
  {"key": "skiploom", "rarity": "common", "value": 500},
  {"key": "jumpluff", "rarity": "uncommon", "value": 1500},
  {"key": "aipom", "rarity": "uncommon", "value": 1500},
  {"key": "sunkern", "rarity": "common", "value": 100},
  {"key": "sunflora", "rarity": "uncommon", "value": 1500},
  {"key": "yanma", "rarity": "uncommon", "value": 1500},
  {"key": "wooper", "rarity": "common", "value": 100},
  {"key": "quagsire", "rarity": "uncommon", "value": 1500},
  {"key": "espeon", "rarity": "epic", "value": 15000},
  {"key": "umbreon", "rarity": "epic", "value": 15000},
  {"key": "murkrow", "rarity": "uncommon", "value": 1500},
  {"key": "slowking", "rarity": "rare", "value": 5000},
  {"key": "misdreavus", "rarity": "uncommon", "value": 1500},
  {"key": "girafarig", "rarity": "rare", "value": 5000},
  {"key": "pineco", "rarity": "common", "value": 100},
  {"key": "forretress", "rarity": "rare", "value": 5000},
  {"key": "dunsparce", "rarity": "rare", "value": 5000},
  {"key": "gligar", "rarity": "uncommon", "value": 1500},
  {"key": "steelix", "rarity": "epic", "value": 15000},
  {"key": "snubbull", "rarity": "common", "value": 100},
  {"key": "granbull", "rarity": "rare", "value": 5000},
  {"key": "qwilfish", "rarity": "uncommon", "value": 1500},
  {"key": "scizor", "rarity": "epic", "value": 15000},
  {"key": "shuckle", "rarity": "rare", "value": 5000},
  {"key": "heracross", "rarity": "epic", "value": 15000},
  {"key": "sneasel", "rarity": "rare", "value": 5000},
  {"key": "teddiursa", "rarity": "common", "value": 100},
  {"key": "ursaring", "rarity": "rare", "value": 5000},
  {"key": "slugma", "rarity": "common", "value": 100},
  {"key": "magcargo", "rarity": "rare", "value": 5000},
  {"key": "swinub", "rarity": "common", "value": 100},
  {"key": "piloswine", "rarity": "uncommon", "value": 1500},
  {"key": "corsola", "rarity": "rare", "value": 5000},
  {"key": "remoraid", "rarity": "common", "value": 100},
  {"key": "octillery", "rarity": "uncommon", "value": 1500},
  {"key": "delibird", "rarity": "rare", "value": 5000},
  {"key": "mantine", "rarity": "rare", "value": 5000},
  {"key": "skarmory", "rarity": "epic", "value": 15000},
  {"key": "houndour", "rarity": "common", "value": 100},
  {"key": "houndoom", "rarity": "rare", "value": 5000},
  {"key": "kingdra", "rarity": "epic", "value": 15000},
  {"key": "phanpy", "rarity": "common", "value": 100},
  {"key": "donphan", "rarity": "rare", "value": 5000},
  {"key": "porygon2", "rarity": "epic", "value": 15000},
  {"key": "stantler", "rarity": "rare", "value": 5000},
  {"key": "smeargle", "rarity": "epic", "value": 15000},
  {"key": "tyrogue", "rarity": "common", "value": 100},
  {"key": "hitmontop", "rarity": "rare", "value": 5000},
  {"key": "smoochum", "rarity": "rare", "value": 5000},
  {"key": "elekid", "rarity": "rare", "value": 5000},
  {"key": "magby", "rarity": "rare", "value": 5000},
  {"key": "miltank", "rarity": "rare", "value": 5000},
  {"key": "blissey", "rarity": "epic", "value": 15000},
  {"key": "raikou", "rarity": "legendary", "value": 50000},
  {"key": "entei", "rarity": "legendary", "value": 50000},
  {"key": "suicune", "rarity": "legendary", "value": 50000},
  {"key": "larvitar", "rarity": "rare", "value": 5000},
  {"key": "pupitar", "rarity": "epic", "value": 15000},
  {"key": "tyranitar", "rarity": "legendary", "value": 50000},
  {"key": "lugia", "rarity": "priceless", "value": 100000},
  {"key": "ho_oh", "rarity": "priceless", "value": 100000},
  {"key": "celebi", "rarity": "priceless", "value": 100000}
]